fixpoint_sdk/__init__.py
fixpoint_sdk/_logging_api.py
fixpoint_sdk/_mock_completions.py
fixpoint_sdk/client.py
fixpoint_sdk/compat.py
fixpoint_sdk/completions.py
fixpoint_sdk/py.typed
fixpoint_sdk/lib/__init__.py
fixpoint_sdk/lib/_mock_requests.py
fixpoint_sdk/lib/debugging.py
fixpoint_sdk/lib/env.py
fixpoint_sdk/lib/exc.py
fixpoint_sdk/lib/iterwrapper.py
fixpoint_sdk/lib/logging.py
fixpoint_sdk/lib/requests.py
fixpoint_sdk/openapi/__init__.py
fixpoint_sdk/openapi/exceptions.py
fixpoint_sdk/types/__init__.py
fixpoint_sdk/types/_utils.py
fixpoint_sdk/types/openai.py
fixpoint_sdk-0.10.0.dist-info/METADATA
fixpoint_sdk-0.10.0.dist-info/WHEEL
fixpoint_sdk-0.10.0.dist-info/licenses/LICENSE
fixpoint_sdk-0.10.0.dist-info/RECORD
