Metadata-Version: 2.3
Name: fixpoint_sdk
Version: 0.10.0
Summary: Python SDK for Fixpoint - Auto-improvement to make your LLM apps smarter
Project-URL: Homepage, https://github.com/gofixpoint/python-sdk
Project-URL: Issues, https://github.com/gofixpoint/python-sdk/issues
Author-email: Fixpoint <team@fixpoint.co>, Jakub Cichon <jakub@fixpoint.co>, Dylan Mikus <dylan@fixpoint.co>
License-File: LICENSE
Classifier: License :: OSI Approved :: Apache Software License
Classifier: Programming Language :: Python :: 3
Requires-Python: >=3.8
Requires-Dist: fixpoint-openapi==0.4.0
Requires-Dist: openai>=1.6.1
Requires-Dist: pydantic>=2
Requires-Dist: python-dateutil>=2.8.2
Requires-Dist: requests==2.31.0
Requires-Dist: typing-extensions>=4.7.1
Provides-Extra: dev
Requires-Dist: black>=24; extra == 'dev'
Requires-Dist: build>=1.1.1; extra == 'dev'
Requires-Dist: ipdb>=0.13.13; extra == 'dev'
Requires-Dist: mypy>=1.8; extra == 'dev'
Requires-Dist: pydantic>=2; extra == 'dev'
Requires-Dist: pylint>=3; extra == 'dev'
Requires-Dist: pytest>=8.0.2; extra == 'dev'
Requires-Dist: python-dateutil>=2.8.2; extra == 'dev'
Requires-Dist: requests-mock>=1.11.0; extra == 'dev'
Requires-Dist: twine>=5.0.0; extra == 'dev'
Requires-Dist: types-requests>=2.31.0; extra == 'dev'
Requires-Dist: typing-extensions>=4.7.1; extra == 'dev'
Requires-Dist: urllib3>=1.25.3; extra == 'dev'
